atrp_calculator/__init__.py
atrp_calculator/calculator.py
atrp_calculator/main.py
atrp_calculator-0.1.0.dist-info/METADATA
atrp_calculator-0.1.0.dist-info/WHEEL
atrp_calculator-0.1.0.dist-info/entry_points.txt
atrp_calculator-0.1.0.dist-info/top_level.txt
atrp_calculator-0.1.0.dist-info/RECORD
