Metadata-Version: 2.4
Name: atrp_calculator
Version: 0.1.0
Summary: A tool to generate ATRP reaction recipes from user-defined molar ratios and stock concentrations.
Author: Cesar Ramirez
Requires-Python: >=3.7
Requires-Dist: pandas
Requires-Dist: openpyxl
Dynamic: author
Dynamic: description
Dynamic: description-content-type
Dynamic: requires-dist
Dynamic: requires-python
Dynamic: summary
